coff/__init__.py
coff/cli.py
confluence_offline-0.1.6.dist-info/COPYING
confluence_offline-0.1.6.dist-info/METADATA
confluence_offline-0.1.6.dist-info/WHEEL
confluence_offline-0.1.6.dist-info/entry_points.txt
confluence_offline-0.1.6.dist-info/top_level.txt
confluence_offline-0.1.6.dist-info/RECORD
