Metadata-Version: 2.1
Name: confluence-offline
Version: 0.1.6
Summary: --
Home-page: https://github.com/volodymyrss/confluence-offline/releases/tag/0.1.0
Author: V.S.
Author-email: vladimir.savchenko@unige.ch
License: GPL-2+
Platform: UNKNOWN
Classifier: Development Status :: 4 - Beta
Classifier: Environment :: Console
Classifier: Intended Audience :: Science/Research
Classifier: License :: OSI Approved :: GNU General Public License v2 or later (GPLv2+)
Classifier: Operating System :: POSIX
Classifier: Programming Language :: Python :: 3.4
Classifier: Programming Language :: Python :: 3.5
Classifier: Programming Language :: Python :: 3.6
Classifier: Programming Language :: Python :: 3.7
Classifier: Topic :: Internet
Classifier: Topic :: Scientific/Engineering
License-File: COPYING
Requires-Dist: lxml
Requires-Dist: six
Requires-Dist: coloredlogs
Requires-Dist: html2text
Requires-Dist: python-dateutil
Requires-Dist: keyring
Requires-Dist: click
